README.rst
setup.py
bin/pfdicom_agesort
pfdicom_agesort/__init__.py
pfdicom_agesort/pfdicom.py
pfdicom_agesort/pfdicom_agesort.py
pfdicom_agesort/pfdicom_tagExtract.py
pfdicom_agesort.egg-info/PKG-INFO
pfdicom_agesort.egg-info/SOURCES.txt
pfdicom_agesort.egg-info/dependency_links.txt
pfdicom_agesort.egg-info/not-zip-safe
pfdicom_agesort.egg-info/requires.txt
pfdicom_agesort.egg-info/top_level.txt