Metadata-Version: 1.0
Name: pfdicom-agesort
Version: 1.0.4
Summary: Process ChRIS trees of DICOM data and reorder by age.
Home-page: https://github.com/FNNDSC/pfdicom_agesort
Author: FNNDSC
Author-email: dev@babymri.org
License: MIT
Platform: UNKNOWN
